perceval/backends/weblate/__init__.py
perceval/backends/weblate/_version.py
perceval/backends/weblate/weblate.py
perceval_weblate-1.1.6.dist-info/METADATA
perceval_weblate-1.1.6.dist-info/WHEEL
perceval_weblate-1.1.6.dist-info/licenses/AUTHORS
perceval_weblate-1.1.6.dist-info/licenses/LICENSE
perceval_weblate-1.1.6.dist-info/RECORD
