Metadata-Version: 2.4
Name: perceval-weblate
Version: 1.1.6
Summary: Bundle of Perceval backends for Weblate.
License: GPL-3.0+
License-File: AUTHORS
License-File: LICENSE
Keywords: development,grimoirelab
Author: GrimoireLab Developers
Requires-Python: >=3.10,<4.0
Classifier: Development Status :: 5 - Production/Stable
Classifier: Intended Audience :: Developers
Classifier: Intended Audience :: Science/Research
Classifier: License :: OSI Approved :: GNU General Public License v3 or later (GPLv3+)
Classifier: Programming Language :: Python :: 3
Classifier: Programming Language :: Python :: 3.10
Classifier: Programming Language :: Python :: 3.11
Classifier: Programming Language :: Python :: 3.12
Classifier: Programming Language :: Python :: 3.13
Classifier: Programming Language :: Python :: 3.14
Classifier: Topic :: Software Development
Requires-Dist: grimoirelab-toolkit (>=0.3)
Requires-Dist: perceval (>=0.19)
Requires-Dist: requests (>=2.7.0,<3.0.0)
Project-URL: Bug Tracker, https://github.com/chaoss/grimoirelab-perceval-weblate/issues
Project-URL: Homepage, https://chaoss.github.io/grimoirelab/
Project-URL: Repository, https://github.com/chaoss/grimoirelab-perceval-weblate
